odoo10_addon_auth_oauth_multi_token-10.0.1.0.0.99.dev3-py2.7-nspkg.pth
odoo/addons/auth_oauth_multi_token/README.rst
odoo/addons/auth_oauth_multi_token/__init__.py
odoo/addons/auth_oauth_multi_token/__manifest__.py
odoo/addons/auth_oauth_multi_token/i18n/auth_oauth_multi_token.pot
odoo/addons/auth_oauth_multi_token/models/__init__.py
odoo/addons/auth_oauth_multi_token/models/auth_oauth_multi_token.py
odoo/addons/auth_oauth_multi_token/models/res_users.py
odoo/addons/auth_oauth_multi_token/security/ir.model.access.csv
odoo/addons/auth_oauth_multi_token/static/description/icon.png
odoo/addons/auth_oauth_multi_token/tests/__init__.py
odoo/addons/auth_oauth_multi_token/tests/test_multi_token.py
odoo/addons/auth_oauth_multi_token/views/res_users.xml
odoo10_addon_auth_oauth_multi_token-10.0.1.0.0.99.dev3.dist-info/METADATA
odoo10_addon_auth_oauth_multi_token-10.0.1.0.0.99.dev3.dist-info/RECORD
odoo10_addon_auth_oauth_multi_token-10.0.1.0.0.99.dev3.dist-info/WHEEL
odoo10_addon_auth_oauth_multi_token-10.0.1.0.0.99.dev3.dist-info/namespace_packages.txt
odoo10_addon_auth_oauth_multi_token-10.0.1.0.0.99.dev3.dist-info/top_level.txt
